csv_diff/__init__.py
csv_diff/cli.py
tests/__init__.py
tests/test_cli.py
tests/test_csv.py
tests/test_csv_diff.py
tests/test_human_text.py
csv_diff_yhua-0.5.4.dist-info/LICENSE
csv_diff_yhua-0.5.4.dist-info/METADATA
csv_diff_yhua-0.5.4.dist-info/WHEEL
csv_diff_yhua-0.5.4.dist-info/entry_points.txt
csv_diff_yhua-0.5.4.dist-info/top_level.txt
csv_diff_yhua-0.5.4.dist-info/RECORD
