Metadata-Version: 2.1
Name: csv-diff-yhua
Version: 0.5.4
Summary: Python CLI tool and library for diffing CSV files
Home-page: https://github.com/MainHanzo/csv-diff-hanzo.git
Author: yhua
License: Apache License, Version 2.0
Platform: UNKNOWN
Classifier: Development Status :: 4 - Beta
Classifier: Intended Audience :: Developers
Classifier: Intended Audience :: Science/Research
Classifier: Intended Audience :: End Users/Desktop
Classifier: License :: OSI Approved :: Apache Software License
Classifier: Programming Language :: Python :: 3.6
Classifier: Programming Language :: Python :: 3.7
Requires-Dist: click
Requires-Dist: dictdiffer
Provides-Extra: test
Requires-Dist: pytest ; extra == 'test'
